README.md
setup.cfg
setup.py
pymultiprocessing/__init__.py
pymultiprocessing/connection.py
pymultiprocessing/forking.py
pymultiprocessing/heap.py
pymultiprocessing/managers.py
pymultiprocessing/pool.py
pymultiprocessing/process.py
pymultiprocessing/queues.py
pymultiprocessing/reduction.py
pymultiprocessing/sharedctypes.py
pymultiprocessing/synchronize.py
pymultiprocessing/threading.py
pymultiprocessing/util.py
pymultiprocessing.egg-info/PKG-INFO
pymultiprocessing.egg-info/SOURCES.txt
pymultiprocessing.egg-info/dependency_links.txt
pymultiprocessing.egg-info/top_level.txt
pymultiprocessing/dummy/__init__.py
pymultiprocessing/dummy/connection.py
pymultiprocessing/dummy/threading.py