Metadata-Version: 1.1
Name: pymultiprocessing
Version: 0.6
Summary: multiprocessing package of python 2.7 
Home-page: https://github.com/sandeep-rawat-xebia/pymultiprocessing.git
Author: Sandeep Rawat
Author-email: san55577@gmail.com
License: UNKNOWN
Download-URL: https://github.com/sandeep-rawat-xebia/pymultiprocessing/releases/download/0.3/pymultiprocessing-0.3.tar.gz
Keywords: multiprocessing,python,jython
Platform: UNKNOWN
